CHANGELOG.rst
LICENSE.txt
MANIFEST.in
README.rst
TODO.rst
VERSION.txt
setup.cfg
setup.py
test-requirements.txt
epoch/__init__.py
epoch/test.py
epoch.egg-info/PKG-INFO
epoch.egg-info/SOURCES.txt
epoch.egg-info/dependency_links.txt
epoch.egg-info/requires.txt
epoch.egg-info/top_level.txt
epoch.egg-info/zip-safe