Metadata-Version: 1.1
Name: epoch
Version: 0.1.5
Summary: A utility library to manage and manipulate UNIX epoch timestamps.
Home-page: http://github.com/metagriffin/epoch
Author: metagriffin
Author-email: mg.pypi@metagriffin.net
License: GPLv3+
Keywords: epoch unix timestamp date time utility
Platform: any
Classifier: Development Status :: 3 - Alpha
Classifier: Environment :: Console
Classifier: Intended Audience :: Developers
Classifier: Intended Audience :: System Administrators
Classifier: Natural Language :: English
Classifier: Operating System :: OS Independent
Classifier: Programming Language :: Python
Classifier: Topic :: Software Development
Classifier: Topic :: Software Development :: Libraries :: Python Modules
Classifier: Topic :: Utilities
Classifier: License :: OSI Approved :: GNU General Public License v3 or later (GPLv3+)
